fast_pareto/__init__.py
fast_pareto/hypervolume.py
fast_pareto/pareto.py
fast_pareto/tie_break.py
fast_pareto-1.0.4.dist-info/LICENSE
fast_pareto-1.0.4.dist-info/METADATA
fast_pareto-1.0.4.dist-info/WHEEL
fast_pareto-1.0.4.dist-info/top_level.txt
fast_pareto-1.0.4.dist-info/RECORD
