Metadata-Version: 2.1
Name: fast-pareto
Version: 1.0.4
Summary: UNKNOWN
Home-page: https://github.com/nabenabe0928/fast_pareto
Author: nabenabe0928
Author-email: shuhei.watanabe.utokyo@gmail.com
License: UNKNOWN
Platform: Linux
Requires-Python: >=3.7
License-File: LICENSE
Requires-Dist: numpy
Requires-Dist: scipy
Requires-Dist: sortedcontainers
